mlrisko/__init__.py
mlrisko/abstention.py
mlrisko/decision/__init__.py
mlrisko/decision/base.py
mlrisko/decision/classification.py
mlrisko/decision/decision.py
mlrisko/decision/regression.py
mlrisko/parameter.py
mlrisko/plot.py
mlrisko/risk.py
mlrisko/risk_control.py
mlrisko/tools/fwer_control.py
mlrisko/tools/pvalues.py
mlrisko-0.1.0.dist-info/licenses/LICENSE
mlrisko-0.1.0.dist-info/WHEEL
mlrisko-0.1.0.dist-info/METADATA
mlrisko-0.1.0.dist-info/RECORD
