Metadata-Version: 2.4
Name: mlrisko
Version: 0.1.0
Summary: A toolkit to calibrate predictive algorithms to achieve risk control.
Keywords: risk-control,machine-learning,ai,statistics,multiple-testing
Author: Thibault Cordier
Author-email: Thibault Cordier <thibault.cordier.pro@gmail.com>
License-Expression: BSD-3-Clause
License-File: LICENSE
Classifier: Programming Language :: Python :: 3.13
Classifier: Operating System :: OS Independent
Classifier: Development Status :: 2 - Pre-Alpha
Classifier: Intended Audience :: Science/Research
Classifier: Intended Audience :: Developers
Classifier: Topic :: Scientific/Engineering :: Artificial Intelligence
Requires-Dist: matplotlib>=3.10.3
Requires-Dist: numpy>=2.3.0
Requires-Dist: scikit-learn>=1.7.0
Maintainer: Thibault Cordier
Maintainer-email: Thibault Cordier <thibault.cordier.pro@gmail.com>
Requires-Python: >=3.13
Project-URL: Bug Tracker, https://github.com/thibaultcordier/risk-control/issues
Project-URL: CI/CD Pipeline, https://github.com/thibaultcordier/risk-control/actions
Project-URL: Changelog, https://github.com/thibaultcordier/risk-control/releases
Project-URL: Code Coverage, https://codecov.io/gh/thibaultcordier/risk-control
Project-URL: Documentation, https://thibaultcordier.github.io/risk-control/
Project-URL: Homepage, https://github.com/thibaultcordier/risk-control
Project-URL: PyPI, https://pypi.org/project/mlrisko/
Project-URL: Source Code, https://github.com/thibaultcordier/risk-control
